pygame_screen_record/EventRegister.py
pygame_screen_record/ScreenRecorder.py
pygame_screen_record/__init__.py
pygame_screen_record/py.typed
pygame_screen_record-0.1.1.dist-info/LICENSE
pygame_screen_record-0.1.1.dist-info/METADATA
pygame_screen_record-0.1.1.dist-info/WHEEL
pygame_screen_record-0.1.1.dist-info/top_level.txt
pygame_screen_record-0.1.1.dist-info/RECORD
