Metadata-Version: 2.1
Name: pygame-screen-record
Version: 0.1.1
Summary: A package that allows you to record your pygame game
Author-email: Rashid Harvey <r.harvey@outlook.de>
Project-URL: Homepage, https://github.com/theRealProHacker/PyGameRecorder
Project-URL: Bug Tracker, https://github.com/theRealProHacker/PyGameRecorder/issues
Classifier: Programming Language :: Python :: 3
Classifier: License :: OSI Approved :: MIT License
Classifier: Operating System :: OS Independent
Requires-Python: >=3.8
License-File: LICENSE
Requires-Dist: opencv-python >=4.7.0.68
Requires-Dist: pygame >=2.1.3
